<annotation>
	<folder>TRUCK</folder>
	<filename>2-032.jpg</filename>
	<size>
		<width>1920</width>
		<height>1080</height>
		<depth>3</depth>
	</size>
	<segmented>0</segmented>
	<object>
		<name>plate</name>
		<pose>Unspecified</pose>
		<truncated>0</truncated>
		<difficult>0</difficult>
		<bndbox>
			<xmin>718</xmin>
			<ymin>489</ymin>
			<xmax>820</xmax>
			<ymax>592</ymax>
		</bndbox>
	</object>
	<object>
		<name>head</name>
		<pose>Unspecified</pose>
		<truncated>1</truncated>
		<difficult>0</difficult>
		<bndbox>
			<xmin>599</xmin>
			<ymin>1</ymin>
			<xmax>1624</xmax>
			<ymax>802</ymax>
		</bndbox>
	</object>
</annotation>
