<annotation>
	<folder>TRUCK</folder>
	<filename>2-185.jpg</filename>
	<size>
		<width>1920</width>
		<height>1080</height>
		<depth>3</depth>
	</size>
	<segmented>0</segmented>
	<object>
		<name>head</name>
		<pose>Unspecified</pose>
		<truncated>1</truncated>
		<difficult>0</difficult>
		<bndbox>
			<xmin>868</xmin>
			<ymin>1</ymin>
			<xmax>1658</xmax>
			<ymax>551</ymax>
		</bndbox>
	</object>
	<object>
		<name>plate</name>
		<pose>Unspecified</pose>
		<truncated>0</truncated>
		<difficult>0</difficult>
		<bndbox>
			<xmin>976</xmin>
			<ymin>295</ymin>
			<xmax>1065</xmax>
			<ymax>371</ymax>
		</bndbox>
	</object>
</annotation>
