<annotation>
	<folder>TRUCK</folder>
	<filename>2-311.jpg</filename>
	<size>
		<width>1920</width>
		<height>1080</height>
		<depth>3</depth>
	</size>
	<segmented>0</segmented>
	<object>
		<name>plate</name>
		<pose>Unspecified</pose>
		<truncated>0</truncated>
		<difficult>0</difficult>
		<bndbox>
			<xmin>712</xmin>
			<ymin>417</ymin>
			<xmax>821</xmax>
			<ymax>510</ymax>
		</bndbox>
	</object>
	<object>
		<name>head</name>
		<pose>Unspecified</pose>
		<truncated>0</truncated>
		<difficult>0</difficult>
		<bndbox>
			<xmin>613</xmin>
			<ymin>9</ymin>
			<xmax>1574</xmax>
			<ymax>823</ymax>
		</bndbox>
	</object>
</annotation>
