<annotation>
	<folder>TRUCK</folder>
	<filename>2-427.jpg</filename>
	<size>
		<width>1920</width>
		<height>1080</height>
		<depth>3</depth>
	</size>
	<segmented>0</segmented>
	<object>
		<name>plate</name>
		<pose>Unspecified</pose>
		<truncated>0</truncated>
		<difficult>0</difficult>
		<bndbox>
			<xmin>781</xmin>
			<ymin>389</ymin>
			<xmax>910</xmax>
			<ymax>486</ymax>
		</bndbox>
	</object>
	<object>
		<name>head</name>
		<pose>Unspecified</pose>
		<truncated>0</truncated>
		<difficult>0</difficult>
		<bndbox>
			<xmin>683</xmin>
			<ymin>26</ymin>
			<xmax>1255</xmax>
			<ymax>727</ymax>
		</bndbox>
	</object>
</annotation>
